{
  "$schema": "../gen/schemas/desktop-schema.json",
  "identifier": "main-capability",
  "description": "主視窗：計時、設定、通知與建立提醒窗所需的最小權限",
  "windows": ["main"],
  "permissions": [
    "core:default",
    "core:window:allow-minimize",
    "core:window:allow-unminimize",
    "core:window:allow-close",
    "core:window:allow-show",
    "core:window:allow-set-focus",
    "core:window:allow-set-always-on-top",
    "core:window:allow-start-dragging",
    "core:window:allow-set-size",
    "core:window:allow-center",
    "core:window:allow-current-monitor",
    "core:webview:allow-create-webview-window",
    "notification:default",
    "store:default",
    "updater:default"
  ]
}
